[{"category":"testing","title":"aaaaaa","cover":"https://thumbs.dreamstime.com/b/nature-river-side-photography-nd-some-random-clicks-78857225.jpg","readTime":{"value":1,"unit":"minute"},"author":{"name":"test","avatar":"https://thumbs.dreamstime.com/b/nature-river-side-photography-nd-some-random-clicks-78857225.jpg"},"content":"<p>hello!</p>","createdAt":"2022-12-22T13:38:26.574Z","id":"1yj2v1yw0lbz4q5ji","comments":{"comments":"test comment"},"updatedAt":"2022-12-22T15:37:41.663Z"},{"category":"testing","title":"bbbbbbb","cover":"https://thumbs.dreamstime.com/b/nature-river-side-photography-nd-some-random-clicks-78857225.jpg","readTime":{"value":1,"unit":"minute"},"author":{"name":"test","avatar":"https://thumbs.dreamstime.com/b/nature-river-side-photography-nd-some-random-clicks-78857225.jpg"},"content":"<p>hello!</p>","createdAt":"2022-12-22T13:38:32.900Z","id":"1yj2v1yw0lbz4qaf8","updatedAt":"2022-12-22T16:31:46.421Z","comments":{"comments":"test another test comment"}},{"category":"testing dsadsadsa dssada","title":"cccccc","cover":"https://thumbs.dreamstime.com/b/nature-river-side-photography-nd-some-random-clicks-78857225.jpg","readTime":{"value":1,"unit":"minute"},"author":{"name":"test","avatar":"https://thumbs.dreamstime.com/b/nature-river-side-photography-nd-some-random-clicks-78857225.jpg"},"content":"<p>hello!</p>","createdAt":"2022-12-22T13:50:13.969Z","id":"1yj2v1yw0lbz55bdd"}]
